{"Приемки":[{"Дата":"2020-10-07 16:00:35","Курьер_GUID":"88f664d5-86d7-4ad3-a928-fd64e880ecf6","Курьер_Код":173,"УникальныйИдентификатор":"3f3e61d9-f39e-4679-914b-ce4e8296b6f1","КоличествоВыпПоПроектам":1,"Номер":359,"Статус приёмки":"generate_doc","КолЗаказовДС":0,"Курьер":"Тухтахунов Бахтиер","Выполнен":6,"Остаток":647965,"ЗарплатаКурьеру":40000},{"Дата":"2020-10-10 11:12:53","Курьер_GUID":"3cf75140-2b85-4924-b637-04c39206d4af","Курьер_Код":179,"УникальныйИдентификатор":"d7ba33a1-0ade-42f2-a615-774cb33885e2","КоличествоВыпПоПроектам":1,"Номер":375,"Статус приёмки":"generate_doc","КолЗаказовДС":0,"Курьер":"Shukur","Выполнен":0,"Остаток":0,"ЗарплатаКурьеру":0},{"Дата":"2020-10-10 13:30:35","Курьер_GUID":"93f535b3-b80e-44e6-b0d5-8d053d26b7e9","Курьер_Код":22,"УникальныйИдентификатор":"5a301925-8d69-4b6b-a37e-4b16f6bc4aaf","КоличествоВыпПоПроектам":1,"Номер":377,"Статус приёмки":"generate_doc","КолЗаказовДС":0,"Курьер":"QOQOND","Выполнен":0,"Остаток":0,"ЗарплатаКурьеру":0},{"Дата":"2020-10-08 13:01:27","Курьер_GUID":"505291c1-590c-4b68-ab80-4e2909cc548f","Курьер_Код":12,"УникальныйИдентификатор":"28386107-b4f9-4f16-b75c-e4d575effdad","КоличествоВыпПоПроектам":1,"Номер":366,"Статус приёмки":"","КолЗаказовДС":0,"Курьер":"FARGONA","Выполнен":6,"Остаток":2059895,"ЗарплатаКурьеру":102000},{"Дата":"2020-10-10 10:21:59","Курьер_GUID":"77534681-21da-4d2e-ab6a-356129177a71","Курьер_Код":12,"УникальныйИдентификатор":"53dd0145-ae2c-4cc9-a0aa-17771a2f111a","КоличествоВыпПоПроектам":1,"Номер":374,"Статус приёмки":null,"КолЗаказовДС":0,"Курьер":"FARGONA","Выполнен":6,"Остаток":2059893,"ЗарплатаКурьеру":102002},{"Дата":"2020-10-09 11:13:58","Курьер_GUID":"e11bbcc9-369f-4e46-8f01-a7c4ce096dc7","Курьер_Код":23,"УникальныйИдентификатор":"feb57a27-85c2-443c-b6c4-217aba469bc9","КоличествоВыпПоПроектам":1,"Номер":370,"Статус приёмки":"generate_doc","КолЗаказовДС":0,"Курьер":"SAMARQAND","Выполнен":0,"Остаток":0,"ЗарплатаКурьеру":0},{"Дата":"2020-10-09 10:24:51","Курьер_GUID":"32dcfc69-72ce-420b-b750-f84fed8317b2","Курьер_Код":30,"УникальныйИдентификатор":"6311b502-23d4-4caa-b2b3-c131969ef716","КоличествоВыпПоПроектам":1,"Номер":369,"Статус приёмки":"generate_doc","КолЗаказовДС":6,"Курьер":"Самарканд","Выполнен":8,"Остаток":3156893,"ЗарплатаКурьеру":292002},{"Дата":"2020-10-09 14:29:28","Курьер_GUID":"91e74eab-077f-4400-86be-f62311c8a771","Курьер_Код":8,"УникальныйИдентификатор":"21a7a3ab-838f-44c5-9654-f06806734e31","КоличествоВыпПоПроектам":1,"Номер":371,"Статус приёмки":null,"КолЗаказовДС":0,"Курьер":"ANDIJAN  BARNO","Выполнен":0,"Остаток":0,"ЗарплатаКурьеру":0},{"Дата":"2020-10-08 15:19:03","Курьер_GUID":"513a3ee4-b1c8-4033-bf63-b19e01a9c35d","Курьер_Код":182,"УникальныйИдентификатор":"8e121e8c-dd9e-4085-8412-bd546056642b","КоличествоВыпПоПроектам":1,"Номер":368,"Статус приёмки":"generate_doc","КолЗаказовДС":0,"Курьер":"Baxtiyor","Выполнен":0,"Остаток":0,"ЗарплатаКурьеру":0},{"Дата":"2020-10-08 11:52:53","Курьер_GUID":"b66c7cd4-8d1b-49d9-9e5d-9e7b3af9e6d6","Курьер_Код":22,"УникальныйИдентификатор":"4ef9e8fa-c4c2-44b3-8a13-86106be8fc3f","КоличествоВыпПоПроектам":1,"Номер":364,"Статус приёмки":"generate_doc","КолЗаказовДС":0,"Курьер":"QOQOND","Выполнен":0,"Остаток":0,"ЗарплатаКурьеру":0},{"Дата":"2020-10-09 15:30:11","Курьер_GUID":"ea6b0013-75e0-44f9-a843-41b623e8db96","Курьер_Код":175,"УникальныйИдентификатор":"b574f9bc-e236-418a-9473-079350cbf178","КоличествоВыпПоПроектам":1,"Номер":373,"Статус приёмки":"","КолЗаказовДС":0,"Курьер":"Шералиев Шукур","Выполнен":0,"Остаток":198000,"ЗарплатаКурьеру":0},{"Дата":"2020-10-08 10:24:13","Курьер_GUID":"4edba326-c8ae-4a27-b446-a4c728abff09","Курьер_Код":2,"УникальныйИдентификатор":"2a8f3991-44dd-4377-b614-bd85bc8afac2","КоличествоВыпПоПроектам":1,"Номер":361,"Статус приёмки":"generate_doc","КолЗаказовДС":0,"Курьер":"SAMARQAND- SARDOR","Выполнен":6,"Остаток":2059895,"ЗарплатаКурьеру":102000},{"Дата":"2020-10-08 11:31:26","Курьер_GUID":"ec010bcd-1925-4dc3-8f1f-56056486e162","Курьер_Код":30,"УникальныйИдентификатор":"b3879e29-699e-4f35-b634-6e7cd2b2c66a","КоличествоВыпПоПроектам":1,"Номер":363,"Статус приёмки":"accept","КолЗаказовДС":8,"Курьер":"Самарканд","Выполнен":0,"Остаток":-495000,"ЗарплатаКурьеру":0},{"Дата":"2020-10-08 13:12:31","Курьер_GUID":"9ad1b9af-d1ad-4d75-86e3-b8b85d391c4a","Курьер_Код":173,"УникальныйИдентификатор":"7c16785e-405f-497f-95f3-75f64bd034c2","КоличествоВыпПоПроектам":1,"Номер":367,"Статус приёмки":"generate_doc","КолЗаказовДС":0,"Курьер":"Тухтахунов Бахтиер","Выполнен":1,"Остаток":371000,"ЗарплатаКурьеру":20000},{"Дата":"2020-10-08 12:03:12","Курьер_GUID":"524be3d7-f05d-49b9-943d-c4c3a0940ecf","Курьер_Код":173,"УникальныйИдентификатор":"7ff5829b-aa01-4f6c-9c08-1b1458fb40d8","КоличествоВыпПоПроектам":1,"Номер":365,"Статус приёмки":"delivered","КолЗаказовДС":1,"Курьер":"Тухтахунов Бахтиер","Выполнен":6,"Остаток":2019895,"ЗарплатаКурьеру":142000},{"Дата":"2020-10-09 15:14:09","Курьер_GUID":"87ab794d-6d70-4a41-b6c2-9df7094ddddd","Курьер_Код":16,"УникальныйИдентификатор":"04da51fc-cce1-424e-91d8-40f156a3b5d8","КоличествоВыпПоПроектам":1,"Номер":372,"Статус приёмки":"","КолЗаказовДС":0,"Курьер":"NAVOI","Выполнен":0,"Остаток":0,"ЗарплатаКурьеру":0}]}