{"Приемки":[{"Дата":"2020-10-07 16:00:35","Курьер_GUID":"f104e98d-7f9d-46fd-bb69-6ef053564364","Курьер_Код":173,"УникальныйИдентификатор":"9cbd7d74-32bf-4c7d-988c-f7d883203d1f","КоличествоВыпПоПроектам":[],"Номер":359,"Статус приёмки":"generate_doc","КолЗаказовДС":0,"Курьер":"Тухтахунов Бахтиер","Выполнен":6,"Остаток":647965,"ЗарплатаКурьеру":40000},{"Дата":"2020-10-10 11:12:53","Курьер_GUID":"d0a8120c-57bd-43cd-b91a-8e4fb03964da","Курьер_Код":179,"УникальныйИдентификатор":"c493fe33-020e-40b8-a47e-bcc322f57f44","КоличествоВыпПоПроектам":[],"Номер":375,"Статус приёмки":"generate_doc","КолЗаказовДС":0,"Курьер":"Shukur","Выполнен":0,"Остаток":0,"ЗарплатаКурьеру":0},{"Дата":"2020-10-10 13:30:35","Курьер_GUID":"56f01ddb-f493-4f44-b9cb-4c644219189c","Курьер_Код":22,"УникальныйИдентификатор":"721c103a-b86f-4656-9680-5a5b5192f305","КоличествоВыпПоПроектам":[],"Номер":377,"Статус приёмки":"generate_doc","КолЗаказовДС":0,"Курьер":"QOQOND","Выполнен":0,"Остаток":0,"ЗарплатаКурьеру":0},{"Дата":"2020-10-08 13:01:27","Курьер_GUID":"30934824-6007-4953-83d9-b85501a4a132","Курьер_Код":12,"УникальныйИдентификатор":"2215023d-1706-49dc-bd35-159606a32068","КоличествоВыпПоПроектам":[],"Номер":366,"Статус приёмки":"","КолЗаказовДС":0,"Курьер":"FARGONA","Выполнен":6,"Остаток":2059895,"ЗарплатаКурьеру":102000},{"Дата":"2020-10-10 10:21:59","Курьер_GUID":"95bbb469-5937-49b0-91bd-5e280ec6c263","Курьер_Код":12,"УникальныйИдентификатор":"3e97d05f-ee0a-4ff4-a288-2206eb7f07a9","КоличествоВыпПоПроектам":[],"Номер":374,"Статус приёмки":null,"КолЗаказовДС":0,"Курьер":"FARGONA","Выполнен":6,"Остаток":2059893,"ЗарплатаКурьеру":102002},{"Дата":"2020-10-09 11:13:58","Курьер_GUID":"80570c6d-efa8-46e6-961c-c574e7524b52","Курьер_Код":23,"УникальныйИдентификатор":"29362f4d-ea77-498a-bcae-6b0c9ae82025","КоличествоВыпПоПроектам":[],"Номер":370,"Статус приёмки":"generate_doc","КолЗаказовДС":0,"Курьер":"SAMARQAND","Выполнен":0,"Остаток":0,"ЗарплатаКурьеру":0},{"Дата":"2020-10-09 10:24:51","Курьер_GUID":"4af60097-2b63-46ca-8fe0-587df16657c1","Курьер_Код":30,"УникальныйИдентификатор":"4a1b3a49-12ef-4662-9084-ded134a79701","КоличествоВыпПоПроектам":[],"Номер":369,"Статус приёмки":"generate_doc","КолЗаказовДС":6,"Курьер":"Самарканд","Выполнен":8,"Остаток":3156893,"ЗарплатаКурьеру":292002},{"Дата":"2020-10-09 14:29:28","Курьер_GUID":"97872d74-900e-4fb5-833d-c72018c54d8f","Курьер_Код":8,"УникальныйИдентификатор":"b2db7e94-7fa0-43db-82bc-c06394294dbf","КоличествоВыпПоПроектам":[],"Номер":371,"Статус приёмки":null,"КолЗаказовДС":0,"Курьер":"ANDIJAN  BARNO","Выполнен":0,"Остаток":0,"ЗарплатаКурьеру":0},{"Дата":"2020-10-08 15:19:03","Курьер_GUID":"dbb06882-3bc6-489c-bad1-2eadc5732e9a","Курьер_Код":182,"УникальныйИдентификатор":"af09f3a3-f07a-4608-9364-bc80a6491c9c","КоличествоВыпПоПроектам":[],"Номер":368,"Статус приёмки":"generate_doc","КолЗаказовДС":0,"Курьер":"Baxtiyor","Выполнен":0,"Остаток":0,"ЗарплатаКурьеру":0},{"Дата":"2020-10-08 11:52:53","Курьер_GUID":"0919ccf4-0ba2-4c8c-9dc0-231b40a6613a","Курьер_Код":22,"УникальныйИдентификатор":"f9f76260-9e88-42be-b350-54792333f769","КоличествоВыпПоПроектам":[],"Номер":364,"Статус приёмки":"generate_doc","КолЗаказовДС":0,"Курьер":"QOQOND","Выполнен":0,"Остаток":0,"ЗарплатаКурьеру":0},{"Дата":"2020-10-09 15:30:11","Курьер_GUID":"227939d7-6e88-4b0f-8ba0-c6f4d0a7a688","Курьер_Код":175,"УникальныйИдентификатор":"3f40c0a6-e24b-4802-8e9e-430545e37bb5","КоличествоВыпПоПроектам":[],"Номер":373,"Статус приёмки":"","КолЗаказовДС":0,"Курьер":"Шералиев Шукур","Выполнен":0,"Остаток":198000,"ЗарплатаКурьеру":0},{"Дата":"2020-10-08 10:24:13","Курьер_GUID":"7eb1edbe-2180-44f2-a078-401683c5c139","Курьер_Код":2,"УникальныйИдентификатор":"34513c73-0e0d-4794-8472-96b0d9ae01b1","КоличествоВыпПоПроектам":[],"Номер":361,"Статус приёмки":"generate_doc","КолЗаказовДС":0,"Курьер":"SAMARQAND- SARDOR","Выполнен":6,"Остаток":2059895,"ЗарплатаКурьеру":102000},{"Дата":"2020-10-08 11:31:26","Курьер_GUID":"250a1440-bf15-4b67-9cbf-c767d7c82025","Курьер_Код":30,"УникальныйИдентификатор":"832516cf-63d4-46cb-bc95-a33d630277c4","КоличествоВыпПоПроектам":[],"Номер":363,"Статус приёмки":"accept","КолЗаказовДС":8,"Курьер":"Самарканд","Выполнен":0,"Остаток":-495000,"ЗарплатаКурьеру":0},{"Дата":"2020-10-08 13:12:31","Курьер_GUID":"81eb2487-55a8-423d-ab23-37f556b80448","Курьер_Код":173,"УникальныйИдентификатор":"2589f150-4edc-4ca1-8395-d880c39b792f","КоличествоВыпПоПроектам":[],"Номер":367,"Статус приёмки":"generate_doc","КолЗаказовДС":0,"Курьер":"Тухтахунов Бахтиер","Выполнен":1,"Остаток":371000,"ЗарплатаКурьеру":20000},{"Дата":"2020-10-08 12:03:12","Курьер_GUID":"d24f7054-fe83-4322-8601-8e0e85b32f45","Курьер_Код":173,"УникальныйИдентификатор":"47eaf7e4-31e9-45ec-801d-6c510f1ce3d4","КоличествоВыпПоПроектам":[],"Номер":365,"Статус приёмки":"delivered","КолЗаказовДС":1,"Курьер":"Тухтахунов Бахтиер","Выполнен":6,"Остаток":2019895,"ЗарплатаКурьеру":142000},{"Дата":"2020-10-09 15:14:09","Курьер_GUID":"6fd4ffd6-583c-448e-8a4c-6cb33c0593e5","Курьер_Код":16,"УникальныйИдентификатор":"72a43bbd-cedf-46c4-aaa6-836767696fb8","КоличествоВыпПоПроектам":[],"Номер":372,"Статус приёмки":"","КолЗаказовДС":0,"Курьер":"NAVOI","Выполнен":0,"Остаток":0,"ЗарплатаКурьеру":0}]}