{"Приемки":[{"УникальныйИдентификатор":1910,"Номер":"1910"},{"УникальныйИдентификатор":1879,"Номер":"1879"},{"УникальныйИдентификатор":1868,"Номер":"1868"},{"УникальныйИдентификатор":1861,"Номер":"1861"},{"УникальныйИдентификатор":1887,"Номер":"1887"},{"УникальныйИдентификатор":1896,"Номер":"1896"},{"УникальныйИдентификатор":1973,"Номер":"1973"},{"УникальныйИдентификатор":1856,"Номер":"1856"},{"УникальныйИдентификатор":1942,"Номер":"1942"},{"УникальныйИдентификатор":1846,"Номер":"1846"},{"УникальныйИдентификатор":1877,"Номер":"1877"},{"УникальныйИдентификатор":1931,"Номер":"1931"},{"УникальныйИдентификатор":1863,"Номер":"1863"},{"УникальныйИдентификатор":1860,"Номер":"1860"},{"УникальныйИдентификатор":1975,"Номер":null},{"УникальныйИдентификатор":1897,"Номер":"1897"},{"УникальныйИдентификатор":1880,"Номер":"1880"},{"УникальныйИдентификатор":1881,"Номер":"1881"},{"УникальныйИдентификатор":1898,"Номер":"1898"},{"УникальныйИдентификатор":1876,"Номер":"1876"},{"УникальныйИдентификатор":1889,"Номер":"1889"},{"УникальныйИдентификатор":1869,"Номер":"1869"},{"УникальныйИдентификатор":1874,"Номер":"1874"},{"УникальныйИдентификатор":1885,"Номер":"1885"},{"УникальныйИдентификатор":1871,"Номер":"1871"},{"УникальныйИдентификатор":1872,"Номер":"1872"},{"УникальныйИдентификатор":1891,"Номер":"1891"},{"УникальныйИдентификатор":1878,"Номер":"1878"},{"УникальныйИдентификатор":1883,"Номер":"1883"},{"УникальныйИдентификатор":1916,"Номер":"1916"},{"УникальныйИдентификатор":1901,"Номер":"1901"},{"УникальныйИдентификатор":1862,"Номер":"1862"},{"УникальныйИдентификатор":1884,"Номер":"1884"},{"УникальныйИдентификатор":1886,"Номер":"1886"},{"УникальныйИдентификатор":1905,"Номер":"1905"},{"УникальныйИдентификатор":1854,"Номер":"1854"},{"УникальныйИдентификатор":1904,"Номер":"1904"},{"УникальныйИдентификатор":1986,"Номер":null},{"УникальныйИдентификатор":1890,"Номер":"1890"},{"УникальныйИдентификатор":1902,"Номер":"1902"},{"УникальныйИдентификатор":1915,"Номер":"1915"},{"УникальныйИдентификатор":1894,"Номер":"1894"},{"УникальныйИдентификатор":1875,"Номер":"1875"},{"УникальныйИдентификатор":1895,"Номер":"1895"},{"УникальныйИдентификатор":1907,"Номер":"1907"},{"УникальныйИдентификатор":1908,"Номер":"1908"},{"УникальныйИдентификатор":1900,"Номер":"1900"},{"УникальныйИдентификатор":1847,"Номер":"1847"},{"УникальныйИдентификатор":1960,"Номер":"1960"},{"УникальныйИдентификатор":1914,"Номер":"1914"},{"УникальныйИдентификатор":1918,"Номер":"1918"},{"УникальныйИдентификатор":1906,"Номер":"1906"},{"УникальныйИдентификатор":1929,"Номер":"1929"},{"УникальныйИдентификатор":1913,"Номер":"1913"},{"УникальныйИдентификатор":1966,"Номер":"1966"},{"УникальныйИдентификатор":1963,"Номер":"1963"},{"УникальныйИдентификатор":1950,"Номер":"1950"},{"УникальныйИдентификатор":1888,"Номер":"1888"},{"УникальныйИдентификатор":1935,"Номер":"1935"},{"УникальныйИдентификатор":1892,"Номер":"1892"},{"УникальныйИдентификатор":1948,"Номер":"1948"},{"УникальныйИдентификатор":1941,"Номер":"1941"},{"УникальныйИдентификатор":1903,"Номер":"1903"},{"УникальныйИдентификатор":1945,"Номер":"1945"},{"УникальныйИдентификатор":1870,"Номер":"1870"},{"УникальныйИдентификатор":1844,"Номер":"1844"},{"УникальныйИдентификатор":1923,"Номер":"1923"},{"УникальныйИдентификатор":1909,"Номер":"1909"},{"УникальныйИдентификатор":1917,"Номер":"1917"},{"УникальныйИдентификатор":1946,"Номер":"1946"},{"УникальныйИдентификатор":1949,"Номер":"1949"},{"УникальныйИдентификатор":1944,"Номер":"1944"},{"УникальныйИдентификатор":1974,"Номер":null},{"УникальныйИдентификатор":1866,"Номер":"1866"},{"УникальныйИдентификатор":1936,"Номер":"1936"},{"УникальныйИдентификатор":1845,"Номер":"1845"},{"УникальныйИдентификатор":1930,"Номер":"1930"},{"УникальныйИдентификатор":1943,"Номер":"1943"},{"УникальныйИдентификатор":1972,"Номер":"1972"},{"УникальныйИдентификатор":1999,"Номер":"1999"},{"УникальныйИдентификатор":1864,"Номер":"1864"},{"УникальныйИдентификатор":1968,"Номер":"1968"},{"УникальныйИдентификатор":1962,"Номер":"1962"},{"УникальныйИдентификатор":1867,"Номер":"1867"},{"УникальныйИдентификатор":1956,"Номер":"1956"},{"УникальныйИдентификатор":1843,"Номер":"1843"},{"УникальныйИдентификатор":1858,"Номер":"1858"},{"УникальныйИдентификатор":1961,"Номер":"8-1854"},{"УникальныйИдентификатор":1842,"Номер":"1842"},{"УникальныйИдентификатор":1859,"Номер":"1859"},{"УникальныйИдентификатор":1951,"Номер":"1951"},{"УникальныйИдентификатор":1857,"Номер":"1857"},{"УникальныйИдентификатор":1971,"Номер":"1971"},{"УникальныйИдентификатор":1952,"Номер":"1952"},{"УникальныйИдентификатор":1955,"Номер":"1955"},{"УникальныйИдентификатор":1976,"Номер":"1976"},{"УникальныйИдентификатор":1893,"Номер":"1893"},{"УникальныйИдентификатор":1865,"Номер":"1865"},{"УникальныйИдентификатор":1848,"Номер":"1848"},{"УникальныйИдентификатор":1852,"Номер":"1852"},{"УникальныйИдентификатор":1977,"Номер":"1977"},{"УникальныйИдентификатор":1967,"Номер":"1967"},{"УникальныйИдентификатор":1899,"Номер":"1899"},{"УникальныйИдентификатор":1996,"Номер":null},{"УникальныйИдентификатор":1873,"Номер":"1873"},{"УникальныйИдентификатор":1882,"Номер":"1882"},{"УникальныйИдентификатор":1997,"Номер":null},{"УникальныйИдентификатор":1998,"Номер":"1998"}]}